Workbook

Sheet Budgeting
B2: Month | C2: Account | D2: Main Category | E2: January | F2: February | G2: March | H2: April | I2: May | J2: June | K2: July | L2: August | M2: September | N2: October | O2: November | P2: Desember
B4: Income Sources
B5: =IFERROR(__xludf.DUMMYFUNCTION("FILTER('Konfigurasi ⚙'!E3:E999, 'Konfigurasi ⚙'!E3:E999<>"""")"),"Monthly Salary") -> Monthly Salary | E5: 5969800 | F5: 6547101
B6: =IFERROR(__xludf.DUMMYFUNCTION("""COMPUTED_VALUE"""),"Freelance/Business") -> Freelance/Business
B7: Total Income | E7: =SUM(E5:E6) -> 5969800 | F7: =SUM(F5:F6) -> 6547101 | G7: =SUM(G5:G6) -> 0 | H7: =SUM(H5:H6) -> 0 | I7: =SUM(I5:I6) -> 0 | J7: =SUM(J5:J6) -> 0 | K7: =SUM(K5:K6) -> 0 | L7: =SUM(L5:L6) -> 0 | ... P7: =SUM(P5:P6) -> 0
N8: ,
B9: Saving List
B10: =IFERROR(__xludf.DUMMYFUNCTION("FILTER('Konfigurasi ⚙'!G3:G999, 'Konfigurasi ⚙'!G3:G999<>"""")"),"General Savings") -> General Savings | C10: Bank Mandiri 2 | E10: 192984 | F10: 694601
B11: =IFERROR(__xludf.DUMMYFUNCTION("""COMPUTED_VALUE"""),"Emergency") -> Emergency | C11: Bank Mandiri
B12: Total Savings | E12: =SUM(E10:E11) -> 192984 | F12: =SUM(F10:F11) -> 694601 | G12: =SUM(G10:G11) -> 0 | H12: =SUM(H10:H11) -> 0 | I12: =SUM(I10:I11) -> 0 | J12: =SUM(J10:J11) -> 0 | K12: =SUM(K10:K11) -> 0 | L12: =SUM(L10:L11) -> 0 | ... P12: =SUM(P10:P11) -> 0
B13: Grand Total | E13: =E12+E22 -> 6054326 | F13: =F12+F22 -> 6547101 | G13: =G12+G22 -> 0 | H13: =H12+H22 -> 0 | I13: =I12+I22 -> 0 | J13: =J12+J22 -> 0 | K13: =K12+K22 -> 0 | L13: =L12+L22 -> 0 | ... P13: =P12+P22 -> 0
B15: Budgeting List
B16: =IFERROR(__xludf.DUMMYFUNCTION("FILTER('Konfigurasi ⚙'!A3:A999, 'Konfigurasi ⚙'!A3:A999<>"""")"),"Kos") -> Kos | C16: Bank Mandiri | E16: 1500000 | F16: 1500000
B17: =IFERROR(__xludf.DUMMYFUNCTION("""COMPUTED_VALUE"""),"Makanan") -> Makanan | C17: Bank Mandiri | E17: 1354784 | F17: 1200000
B18: =IFERROR(__xludf.DUMMYFUNCTION("""COMPUTED_VALUE"""),"Skincare") -> Skincare | C18: Bank Mandiri | E18: 175402 | F18: 200000
B19: =IFERROR(__xludf.DUMMYFUNCTION("""COMPUTED_VALUE"""),"Self-reward") -> Self-reward | C19: Bank Mandiri | E19: 154500 | F19: 200000
B20: =IFERROR(__xludf.DUMMYFUNCTION("""COMPUTED_VALUE"""),"Transfer") -> Transfer | C20: Bank Mandiri | E20: 1100000 | F20: 1100000
B21: =IFERROR(__xludf.DUMMYFUNCTION("""COMPUTED_VALUE"""),"Lainnya") -> Lainnya | C21: Bank Mandiri | E21: 1576656 | F21: 1652500
B22: Total | E22: =SUM(E16:E21) -> 5861342 | F22: =SUM(F16:F21) -> 5852500 | G22: =SUM(G16:G21) -> 0 | H22: =SUM(H16:H21) -> 0 | I22: =SUM(I16:I21) -> 0 | J22: =SUM(J16:J21) -> 0 | K22: =SUM(K16:K21) -> 0 | L22: =SUM(L16:L21) -> 0 | ... P22: =SUM(P16:P21) -> 0
B24: Allocated Money | E24: =IFERROR(E13/E7,"") -> 1.0141589 | F24: =IFERROR(F13/F7,"") -> 1 | G24: =IFERROR(G13/G7,"") | H24: =IFERROR(H13/H7,"") | I24: =IFERROR(I13/I7,"") | J24: =IFERROR(J13/J7,"") | K24: =IFERROR(K13/K7,"") | L24: =IFERROR(L13/L7,"") | ... P24: =IFERROR(P13/P7,"")
B25: Non-allocated Money | E25: =E7-E13 -> -84526 | F25: =F7-F13 -> 0 | G25: =G7-G13 -> 0 | H25: =H7-H13 -> 0 | I25: =I7-I13 -> 0 | J25: =J7-J13 -> 0 | K25: =K7-K13 -> 0 | L25: =L7-L13 -> 0 | ... P25: =P7-P13 -> 0

Sheet Spending Tracker
B2: Spending Tracker
B4: ✔ | C4: Date | D4: Description | E4: Category | F4: Total | G4: Account
B6: FALSE | C6: 46023 | D6: Transfer | E6: Transfer | F6: 1100000 | G6: Bank Mandiri
B7: FALSE | C7: 46023 | D7: Sedekah | E7: Lainnya | F7: 152500 | G7: Bank Mandiri
B8: FALSE | C8: 46023 | D8: Fee Transfer | E8: Lainnya | F8: 2500 | G8: Bank Mandiri
B9: FALSE | C9: 46023 | D9: Gojek | E9: Lainnya | F9: 36000 | G9: Bank Mandiri
B10: FALSE | C10: 46023 | D10: KRL | E10: Lainnya | F10: 9000 | G10: Bank Mandiri
B11: FALSE | C11: 46023 | D11: Telur dll | E11: Lainnya | F11: 74800 | G11: Bank Mandiri
B12: FALSE | C12: 46023 | D12: Jajan | E12: Makanan | F12: 40000 | G12: Bank Mandiri
B13: FALSE | C13: 46023 | D13: Skincare + Make up | E13: Skincare | F13: 138902 | G13: Bank Mandiri
B14: FALSE | C14: 46023 | D14: Bensin | E14: Lainnya | F14: 45000 | G14: Bank Mandiri
B15: FALSE | C15: 46023 | D15: Dimsum | E15: Makanan | F15: 28000 | G15: Bank Mandiri
B16: FALSE | C16: 46023 | D16: Kuota Cely | E16: Lainnya | F16: 50000 | G16: Bank Mandiri
B17: FALSE | C17: 46023 | D17: Udunan Ka DTU | E17: Lainnya | F17: 50000 | G17: Bank Mandiri
... B70: FALSE | C70: 46069 | D70: Sedekah | E70: Lainnya | F70: 5000 | G70: Bank Mandiri
B71: FALSE
B72: FALSE
B73: FALSE
B74: FALSE
B75: FALSE
B76: FALSE
B77: FALSE
B78: FALSE
B79: FALSE
B80: FALSE
B81: FALSE
B82: FALSE
... B851: FALSE

Sheet Report
B1: Money Management Dashboard 💸 | I1: Year : | J1: 2026
I2: Month : | J2: February
B4: Monthly Report 📊
B6: Total Income | F6: =J2&" Savings" -> February Savings | J6: =J2&" Spendings" -> February Spendings
B7: =IFERROR(VLOOKUP("Total Income", Budgeting!B:P, MATCH($J$2, Budgeting!B2:P2, 0), 0),"") -> 6547101 | F7: =IFERROR(VLOOKUP("Total Savings", Budgeting!B:P, MATCH($J$2, Budgeting!B2:P2, 0), 0),"") -> 694601 | J7: =SUMIFS('Spending Tracker'!F:F, 'Spending Tracker'!C:C, ">="&DATE($J$1,MATCH($J$2,Budgeting!$E$2:$P$2,0),1), 'Spending Tracker'!C:C, "<="&EOMONTH(DATE($J$1,MATCH($J$2,Budgeting!$E$2:$P$2,0),1),0)) -> 5116547
B9: Expenses | D9: Allocation 💰 | F9: Realization 💸 | H9: Budget Usage Progress | J9: % Usage
B10: =IFERROR(__xludf.DUMMYFUNCTION("FILTER('Konfigurasi ⚙'!A3:A997, 'Konfigurasi ⚙'!A3:A997<>"""")"),"Kos") -> Kos | D10: =IFERROR(VLOOKUP(B10, Budgeting!B:P, MATCH($J$2, Budgeting!B2:P2, 0), 0),"") -> 1500000 | F10: =SUMIFS('Spending Tracker'!F:F, 'Spending Tracker'!E:E, B10, 'Spending Tracker'!C:C, ">="&DATE($J$1,MATCH($J$2,Budgeting!$E$2:$P$2,0),1), 'Spending Tracker'!C:C, "<="&EOMONTH(DATE($J$1,MATCH($J$2,Budgeting!$E$2:$P$2,0),1),0)) -> 1500000 | H10: =IFERROR(__xludf.DUMMYFUNCTION("SPARKLINE(J10, {""charttype"",""bar""; ""max"",1; ""color1"",IF(J10>1,""red"",""teal"")})"),"") | J10: =IFERROR(F10/D10,"") -> 1
B11: =IFERROR(__xludf.DUMMYFUNCTION("""COMPUTED_VALUE"""),"Makanan") -> Makanan | D11: =IFERROR(VLOOKUP(B11, Budgeting!B:P, MATCH($J$2, Budgeting!B2:P2, 0), 0),"") -> 1200000 | F11: =SUMIFS('Spending Tracker'!F:F, 'Spending Tracker'!E:E, B11, 'Spending Tracker'!C:C, ">="&DATE($J$1,MATCH($J$2,Budgeting!$E$2:$P$2,0),1), 'Spending Tracker'!C:C, "<="&EOMONTH(DATE($J$1,MATCH($J$2,Budgeting!$E$2:$P$2,0),1),0)) -> 1196788 | H11: =IFERROR(__xludf.DUMMYFUNCTION("SPARKLINE(J11, {""charttype"",""bar""; ""max"",1; ""color1"",IF(J11>1,""red"",""teal"")})"),"") | J11: =IFERROR(F11/D11,"") -> 0.99732333
B12: =IFERROR(__xludf.DUMMYFUNCTION("""COMPUTED_VALUE"""),"Skincare") -> Skincare | D12: =IFERROR(VLOOKUP(B12, Budgeting!B:P, MATCH($J$2, Budgeting!B2:P2, 0), 0),"") -> 200000 | F12: =SUMIFS('Spending Tracker'!F:F, 'Spending Tracker'!E:E, B12, 'Spending Tracker'!C:C, ">="&DATE($J$1,MATCH($J$2,Budgeting!$E$2:$P$2,0),1), 'Spending Tracker'!C:C, "<="&EOMONTH(DATE($J$1,MATCH($J$2,Budgeting!$E$2:$P$2,0),1),0)) -> 0 | H12: =IFERROR(__xludf.DUMMYFUNCTION("SPARKLINE(J12, {""charttype"",""bar""; ""max"",1; ""color1"",IF(J12>1,""red"",""teal"")})"),"") | J12: =IFERROR(F12/D12,"") -> 0
B13: =IFERROR(__xludf.DUMMYFUNCTION("""COMPUTED_VALUE"""),"Self-reward") -> Self-reward | D13: =IFERROR(VLOOKUP(B13, Budgeting!B:P, MATCH($J$2, Budgeting!B2:P2, 0), 0),"") -> 200000 | F13: =SUMIFS('Spending Tracker'!F:F, 'Spending Tracker'!E:E, B13, 'Spending Tracker'!C:C, ">="&DATE($J$1,MATCH($J$2,Budgeting!$E$2:$P$2,0),1), 'Spending Tracker'!C:C, "<="&EOMONTH(DATE($J$1,MATCH($J$2,Budgeting!$E$2:$P$2,0),1),0)) -> 200000 | H13: =IFERROR(__xludf.DUMMYFUNCTION("SPARKLINE(J13, {""charttype"",""bar""; ""max"",1; ""color1"",IF(J13>1,""red"",""teal"")})"),"") | J13: =IFERROR(F13/D13,"") -> 1
B14: =IFERROR(__xludf.DUMMYFUNCTION("""COMPUTED_VALUE"""),"Transfer") -> Transfer | D14: =IFERROR(VLOOKUP(B14, Budgeting!B:P, MATCH($J$2, Budgeting!B2:P2, 0), 0),"") -> 1100000 | F14: =SUMIFS('Spending Tracker'!F:F, 'Spending Tracker'!E:E, B14, 'Spending Tracker'!C:C, ">="&DATE($J$1,MATCH($J$2,Budgeting!$E$2:$P$2,0),1), 'Spending Tracker'!C:C, "<="&EOMONTH(DATE($J$1,MATCH($J$2,Budgeting!$E$2:$P$2,0),1),0)) -> 1100000 | H14: =IFERROR(__xludf.DUMMYFUNCTION("SPARKLINE(J14, {""charttype"",""bar""; ""max"",1; ""color1"",IF(J14>1,""red"",""teal"")})"),"") | J14: =IFERROR(F14/D14,"") -> 1
B15: =IFERROR(__xludf.DUMMYFUNCTION("""COMPUTED_VALUE"""),"Lainnya") -> Lainnya | D15: =IFERROR(VLOOKUP(B15, Budgeting!B:P, MATCH($J$2, Budgeting!B2:P2, 0), 0),"") -> 1652500 | F15: =SUMIFS('Spending Tracker'!F:F, 'Spending Tracker'!E:E, B15, 'Spending Tracker'!C:C, ">="&DATE($J$1,MATCH($J$2,Budgeting!$E$2:$P$2,0),1), 'Spending Tracker'!C:C, "<="&EOMONTH(DATE($J$1,MATCH($J$2,Budgeting!$E$2:$P$2,0),1),0)) -> 1119759 | H15: =IFERROR(__xludf.DUMMYFUNCTION("SPARKLINE(J15, {""charttype"",""bar""; ""max"",1; ""color1"",IF(J15>1,""red"",""teal"")})"),"") | J15: =IFERROR(F15/D15,"") -> 0.67761513
B17: Expense Realization Price | F17: Monthly Expense Trend
L76: January | M76: =SUMIFS('Spending Tracker'!F:F, 'Spending Tracker'!C:C, ">="&DATE($J$1,1,1), 'Spending Tracker'!C:C, "<="&EOMONTH(DATE($J$1,1,1),0)) -> 5668358
L77: February | M77: =SUMIFS('Spending Tracker'!F:F, 'Spending Tracker'!C:C, ">="&DATE($J$1,2,1), 'Spending Tracker'!C:C, "<="&EOMONTH(DATE($J$1,2,1),0)) -> 5116547
L78: March | M78: =SUMIFS('Spending Tracker'!F:F, 'Spending Tracker'!C:C, ">="&DATE($J$1,3,1), 'Spending Tracker'!C:C, "<="&EOMONTH(DATE($J$1,3,1),0)) -> 0
L79: April | M79: =SUMIFS('Spending Tracker'!F:F, 'Spending Tracker'!C:C, ">="&DATE($J$1,4,1), 'Spending Tracker'!C:C, "<="&EOMONTH(DATE($J$1,4,1),0)) -> 0
L80: May | M80: =SUMIFS('Spending Tracker'!F:F, 'Spending Tracker'!C:C, ">="&DATE($J$1,5,1), 'Spending Tracker'!C:C, "<="&EOMONTH(DATE($J$1,5,1),0)) -> 0
L81: June | M81: =SUMIFS('Spending Tracker'!F:F, 'Spending Tracker'!C:C, ">="&DATE($J$1,6,1), 'Spending Tracker'!C:C, "<="&EOMONTH(DATE($J$1,6,1),0)) -> 0
L82: July | M82: =SUMIFS('Spending Tracker'!F:F, 'Spending Tracker'!C:C, ">="&DATE($J$1,7,1), 'Spending Tracker'!C:C, "<="&EOMONTH(DATE($J$1,7,1),0)) -> 0
L83: August | M83: =SUMIFS('Spending Tracker'!F:F, 'Spending Tracker'!C:C, ">="&DATE($J$1,8,1), 'Spending Tracker'!C:C, "<="&EOMONTH(DATE($J$1,8,1),0)) -> 0
L84: September | M84: =SUMIFS('Spending Tracker'!F:F, 'Spending Tracker'!C:C, ">="&DATE($J$1,9,1), 'Spending Tracker'!C:C, "<="&EOMONTH(DATE($J$1,9,1),0)) -> 0
L85: October | M85: =SUMIFS('Spending Tracker'!F:F, 'Spending Tracker'!C:C, ">="&DATE($J$1,10,1), 'Spending Tracker'!C:C, "<="&EOMONTH(DATE($J$1,10,1),0)) -> 0
L86: November | M86: =SUMIFS('Spending Tracker'!F:F, 'Spending Tracker'!C:C, ">="&DATE($J$1,11,1), 'Spending Tracker'!C:C, "<="&EOMONTH(DATE($J$1,11,1),0)) -> 0
L87: December | M87: =SUMIFS('Spending Tracker'!F:F, 'Spending Tracker'!C:C, ">="&DATE($J$1,12,1), 'Spending Tracker'!C:C, "<="&EOMONTH(DATE($J$1,12,1),0)) -> 0

Sheet Summary
B2: Year : | C2: 2026 | E2: Melanie Despitasari | G2: Month | H2: January
B3: Budgeting Summary
B5: Bank Mandiri | D5: =SUMPRODUCT((Budgeting!$C:$C=B5)*(Budgeting!$E$2:$P$2=$H$2),Budgeting!$E:$P) -> 5861342 | E5: Needs | F5: =SUMPRODUCT((Budgeting!$D:$D=E5)*(Budgeting!$E$2:$P$2=$H$2),Budgeting!$E:$P) -> 0 | G5: Total Income | H5: =VLOOKUP("Total Income",Budgeting!B:P,MATCH($H$2,Budgeting!$B$2:$P$2,0),0) -> 5969800
B6: Bank Mandiri 2 | D6: =SUMPRODUCT((Budgeting!$C:$C=B6)*(Budgeting!$E$2:$P$2=$H$2),Budgeting!$E:$P) -> 192984 | E6: Wants | F6: =SUMPRODUCT((Budgeting!$D:$D=E6)*(Budgeting!$E$2:$P$2=$H$2),Budgeting!$E:$P) -> 0 | G6: Non-allocated | H6: =VLOOKUP("Non-allocated Money",Budgeting!B:P,MATCH($H$2,Budgeting!$B$2:$P$2,0),0) -> -84526
B7: E-wallet | D7: =SUMPRODUCT((Budgeting!$C:$C=B7)*(Budgeting!$E$2:$P$2=$H$2),Budgeting!$E:$P) -> 0 | E7: Savings | F7: =SUMPRODUCT((Budgeting!$D:$D=E7)*(Budgeting!$E$2:$P$2=$H$2),Budgeting!$E:$P) -> 0 | G7: Usage Percentage | H7: =VLOOKUP("Allocated Money",Budgeting!B:P,MATCH($H$2,Budgeting!$B$2:$P$2,0),0) -> 1.0141589
B9: Account | D9: Expenses List | E9: Main Category | F9: Allocation | H9: Percentage
B10: ✔
B11: FALSE | C11: Bank Mandiri 2 | D11: General Savings | E11: Savings | F11: =IFERROR(VLOOKUP(D11,Budgeting!B:P,MATCH($H$2,Budgeting!$E$2:$P$2,0)+3,0),"") -> 192984 | H11: =IFERROR(F11/$H$5,"") -> 0.032326711
B12: FALSE | C12: Bank Mandiri | D12: Emergency | E12: Savings | F12: =IFERROR(VLOOKUP(D12,Budgeting!B:P,MATCH($H$2,Budgeting!$E$2:$P$2,0)+3,0),"") | H12: =IFERROR(F12/$H$5,"") -> 0
B13: FALSE | C13: Bank Mandiri | D13: Kos | E13: Needs | F13: =IFERROR(VLOOKUP(D13,Budgeting!B:P,MATCH($H$2,Budgeting!$E$2:$P$2,0)+3,0),"") -> 1500000 | H13: =IFERROR(F13/$H$5,"") -> 0.2512647
B14: FALSE | C14: Bank Mandiri | D14: Makanan | E14: Needs | F14: =IFERROR(VLOOKUP(D14,Budgeting!B:P,MATCH($H$2,Budgeting!$E$2:$P$2,0)+3,0),"") -> 1354784 | H14: =IFERROR(F14/$H$5,"") -> 0.2269396
B15: FALSE | C15: Bank Mandiri | D15: Skincare | E15: Needs | F15: =IFERROR(VLOOKUP(D15,Budgeting!B:P,MATCH($H$2,Budgeting!$E$2:$P$2,0)+3,0),"") -> 175402 | H15: =IFERROR(F15/$H$5,"") -> 0.029381554
B16: FALSE | C16: Bank Mandiri | D16: Self-Reward | E16: Wants | F16: =IFERROR(VLOOKUP(D16,Budgeting!B:P,MATCH($H$2,Budgeting!$E$2:$P$2,0)+3,0),"") -> 154500 | H16: =IFERROR(F16/$H$5,"") -> 0.025880264
B17: FALSE | C17: Bank Mandiri | D17: Transfer | E17: Needs | F17: =IFERROR(VLOOKUP(D17,Budgeting!B:P,MATCH($H$2,Budgeting!$E$2:$P$2,0)+3,0),"") -> 1100000 | H17: =IFERROR(F17/$H$5,"") -> 0.18426078
B18: FALSE | C18: Bank Mandiri | D18: Lainnya | E18: Wants | F18: =IFERROR(VLOOKUP(D18,Budgeting!B:P,MATCH($H$2,Budgeting!$E$2:$P$2,0)+3,0),"") -> 1576656 | H18: =IFERROR(F18/$H$5,"") -> 0.26410533
D19: Total | F19: =IFERROR(VLOOKUP(D19,Budgeting!B:P,MATCH($H$2,Budgeting!$E$2:$P$2,0)+3,0),"") -> 5861342 | H19: =IFERROR(F19/$H$5,"") -> 0.98183222
C70: Payday | D70: 45716

Sheet Konfigurasi ⚙
A1: Daftar Kategori | D1: Daftar Akun | E1: Sumber Pemasukan | G1: Tujuan Tabungan
A2: Kategori Pengeluaran | B2: Klasifikasi | D2: Nama Akun | E2: Sumber | G2: Tujuan
A3: Kos | B3: Needs | D3: Bank Mandiri | E3: Monthly Salary | G3: General Savings
A4: Makanan | B4: Needs | D4: Bank Mandiri 2 | E4: Freelance/Business | G4: Emergency
A5: Skincare | B5: Needs
A6: Self-reward | B6: Wants
A7: Transfer | B7: Needs
A8: Lainnya | B8: Wants
